core/__init__.py
core/utils.py
milktea-0.0.1.dist-info/LICENSE
milktea-0.0.1.dist-info/METADATA
milktea-0.0.1.dist-info/WHEEL
milktea-0.0.1.dist-info/top_level.txt
milktea-0.0.1.dist-info/RECORD
